gym_trading/__init__.py
gym_trading/_modidx.py
gym_trading/core.py
gym_trading/data/__init__.py
gym_trading/data/download.py
gym_trading/environements/__init__.py
gym_trading/environements/crypto.py
gym_trading/environments/__init__.py
gym_trading/environments/basic.py
gym_trading-0.0.2.dist-info/LICENSE
gym_trading-0.0.2.dist-info/METADATA
gym_trading-0.0.2.dist-info/WHEEL
gym_trading-0.0.2.dist-info/entry_points.txt
gym_trading-0.0.2.dist-info/top_level.txt
gym_trading-0.0.2.dist-info/RECORD
