Metadata-Version: 2.1
Name: gym-trading
Version: 0.0.2
Summary: Trading environments for Gymnasium
Home-page: https://github.com/neurion-ai/gym-trading
Author: Synthetic Monad
Author-email: synth@neurion.ai
License: MIT License
Keywords: nbdev jupyter notebook python
Classifier: Development Status :: 4 - Beta
Classifier: Intended Audience :: Developers
Classifier: Natural Language :: English
Classifier: Programming Language :: Python :: 3.10
Classifier: Programming Language :: Python :: 3.11
Classifier: Programming Language :: Python :: 3.12
Classifier: License :: OSI Approved :: MIT License
Requires-Python: >=3.10
License-File: LICENSE
Requires-Dist: fastcore
Requires-Dist: pandas
Requires-Dist: gymnasium
Requires-Dist: numpy
Requires-Dist: ccxt
Requires-Dist: asyncio
Requires-Dist: nest-asyncio
Provides-Extra: dev
